podcast_charts/__init__.py
podcast_charts/admin.py
podcast_charts/apps.py
podcast_charts/exceptions.py
podcast_charts/models.py
podcast_charts/py.typed
podcast_charts/urls.py
podcast_charts/views.py
podcast_charts/backends/__init__.py
podcast_charts/backends/apple.py
podcast_charts/templates/base.html
podcast_charts/templates/podcast_charts/app_base.html
django_podcast_charts-0.0.1.dist-info/METADATA
django_podcast_charts-0.0.1.dist-info/WHEEL
django_podcast_charts-0.0.1.dist-info/licenses/LICENSE
django_podcast_charts-0.0.1.dist-info/RECORD
