Metadata-Version: 2.4
Name: django-podcast-charts
Version: 0.0.1
Summary: An app to track podcast chart positions from various services.
Project-URL: Repository, https://github.com/andrlik/django-podcast-charts
Project-URL: Homepage, https://github.com/andrlik/django-podcast-charts
Project-URL: Documentation, https://andrlik.github.io/django-podcast-charts
Author-email: Daniel Andrlik <daniel@andrlik.org>
License-File: LICENSE
Classifier: Development Status :: 2 - Pre-Alpha
Classifier: Framework :: Django
Classifier: Framework :: Django :: 5.0
Classifier: Framework :: Django :: 5.1
Classifier: License :: OSI Approved :: BSD License
Classifier: Programming Language :: Python :: 3.12
Classifier: Programming Language :: Python :: 3.13
Requires-Python: >=3.12
Requires-Dist: beautifulsoup4>=4.12.3
Requires-Dist: django>=5.1.4
Requires-Dist: httpx[brotli,http2]>=0.28.1
